srsly_cli/__init__.py
srsly_cli/__main__.py
srsly_cli/srsly_convert.py
srsly_cli/utils.py
srsly_cli-0.0.1.dist-info/LICENSE
srsly_cli-0.0.1.dist-info/METADATA
srsly_cli-0.0.1.dist-info/WHEEL
srsly_cli-0.0.1.dist-info/entry_points.txt
srsly_cli-0.0.1.dist-info/top_level.txt
srsly_cli-0.0.1.dist-info/RECORD
